main.py
genai_observable_sdk-1.1.1.dist-info/METADATA
genai_observable_sdk-1.1.1.dist-info/WHEEL
genai_observable_sdk-1.1.1.dist-info/setup.py
genai_observable_sdk-1.1.1.dist-info/top_level.txt
genai_observable_sdk-1.1.1.dist-info/RECORD
