Metadata-Version: 2.4
Name: genai-observable-sdk
Version: 1.1.1
Summary: Integrated langfuse
Requires-Python: >=3.12
Requires-Dist: setuptools>=80.9.0
